laboris/__init__.py
laboris/commands/__init__.py
laboris/commands/create.py
laboris/commands/delete.py
laboris/commands/done.py
laboris/commands/start.py
laboris/commands/stop.py
laboris/commands/update.py
laboris/main.py
laboris/model.py
laboris/reports/burndown.py
laboris/reports/detail.py
laboris/reports/gantt.py
laboris/reports/graph.py
laboris/reports/list.py
laboris/reports/summary.py
laboris/ui.py
laboris/util.py
laboris-0.1.1.dist-info/entry_points.txt
laboris-0.1.1.dist-info/WHEEL
laboris-0.1.1.dist-info/METADATA
laboris-0.1.1.dist-info/RECORD
