Metadata-Version: 2.1
Name: laboris
Version: 0.1.1
Summary: 
Author: Arden Rasmussen
Author-email: ardenisthebest@gmail.com
Requires-Python: >=3.9,<4.0
Classifier: Programming Language :: Python :: 3
Classifier: Programming Language :: Python :: 3.10
Classifier: Programming Language :: Python :: 3.9
Requires-Dist: click (>=8.0.3,<9.0.0)
Requires-Dist: halo (>=0.0.31,<0.0.32)
Requires-Dist: humanize (>=4.0.0,<5.0.0)
Requires-Dist: isodate (>=0.6.1,<0.7.0)
Requires-Dist: pony (>=0.7.16,<0.8.0)
Requires-Dist: python-dateutil (>=2.8.2,<3.0.0)
Requires-Dist: rich (>=11.2.0,<12.0.0)
